arranjo_combinacao/__init__.py
arranjo_combinacao/arranjo.py
arranjo_combinacao/combinacao.py
arranjo_combinacao-0.0.2.dist-info/METADATA
arranjo_combinacao-0.0.2.dist-info/WHEEL
arranjo_combinacao-0.0.2.dist-info/top_level.txt
arranjo_combinacao-0.0.2.dist-info/RECORD
