Metadata-Version: 2.1
Name: arranjo-combinacao
Version: 0.0.2
Summary: Cálculo simples de arranjo e combinação
Home-page: https://github.com/DanielPaes/simple-package-template.git
Author: daniel_paes
Author-email: daniel92.dev@gmail.com
Requires-Python: >=3.8
